<?xml version="1.0" encoding="utf-8"?>
<LanguageData>

  <ra2_GrizzlyTank.label>Grizzly Tank</ra2_GrizzlyTank.label>
  <ra2_GrizzlyTank.labelPlural>Grizzly Tank</ra2_GrizzlyTank.labelPlural>
  <ra2_GrizzlyTank.labelMale>male Grizzly Tank</ra2_GrizzlyTank.labelMale>
  <ra2_GrizzlyTank.labelMalePlural>male Grizzly Tanks</ra2_GrizzlyTank.labelMalePlural>
  <ra2_GrizzlyTank.labelFemale>female Grizzly Tank</ra2_GrizzlyTank.labelFemale>
  <ra2_GrizzlyTank.labelFemalePlural>female Grizzly Tanks</ra2_GrizzlyTank.labelFemalePlural>


</LanguageData>