<?xml version="1.0" encoding="utf-8"?>
<LanguageData>

  <ra2_GrandCannon.label>Grand Cannon</ra2_GrandCannon.label>
  <ra2_GrandCannon.description>The Allied's defensive weapons,can launch huge shells and cause extensive damage.Can cross the fence to attack the enemy.</ra2_GrandCannon.description>

  <ra2_Bullet_GrandCannon.label>Grand Cannon</ra2_Bullet_GrandCannon.label>

  <ra2_Gun_GrandCannon.label>Grand Cannon</ra2_Gun_GrandCannon.label>
  <ra2_Gun_GrandCannon.description>Powerful Grand Cannon。</ra2_Gun_GrandCannon.description>


</LanguageData>